shinigami/__init__.py
shinigami/cli.py
shinigami/core/__init__.py
shinigami/modules/__init__.py
shinigami/modules/cve_scanner.py
shinigami/modules/dns_enum.py
shinigami/modules/osint.py
shinigami/modules/port_scanner.py
shinigami/modules/ssl_analyzer.py
shinigami/modules/web_recon.py
shinigami/modules/web_screenshot.py
shinigami/utils/__init__.py
shinigami/utils/ascii_art.py
shinigami/utils/logger.py
shinigami/utils/report.py
shinigami_eye-2.0.0.dist-info/METADATA
shinigami_eye-2.0.0.dist-info/WHEEL
shinigami_eye-2.0.0.dist-info/entry_points.txt
shinigami_eye-2.0.0.dist-info/RECORD
