Metadata-Version: 2.4
Name: shinigami-eye
Version: 2.0.0
Summary: All-Seeing Cybersecurity Framework for Network Reconnaissance and Vulnerability Assessment
License: MIT
Keywords: cybersecurity,reconnaissance,pentesting,security,network,scanner,cve,osint
Author: Mauro
Author-email: maauro.rs@gmail.com
Requires-Python: >=3.8.1,<4.0.0
Classifier: Development Status :: 4 - Beta
Classifier: Environment :: Console
Classifier: Intended Audience :: Developers
Classifier: Intended Audience :: Information Technology
Classifier: Intended Audience :: System Administrators
Classifier: License :: OSI Approved :: MIT License
Classifier: Operating System :: OS Independent
Classifier: Programming Language :: Python :: 3
Classifier: Programming Language :: Python :: 3.9
Classifier: Programming Language :: Python :: 3.10
Classifier: Programming Language :: Python :: 3.11
Classifier: Programming Language :: Python :: 3.12
Classifier: Programming Language :: Python :: 3.13
Classifier: Programming Language :: Python :: 3.14
Classifier: Programming Language :: Python :: 3.8
Classifier: Topic :: Security
Classifier: Topic :: System :: Networking
Classifier: Topic :: Utilities
Requires-Dist: Jinja2 (>=3.1.2,<4.0.0)
Requires-Dist: PyYAML (>=6.0,<7.0)
Requires-Dist: beautifulsoup4 (>=4.11.0,<5.0.0)
Requires-Dist: colorama (>=0.4.6,<0.5.0)
Requires-Dist: dnspython (>=2.3.0,<3.0.0)
Requires-Dist: lxml (>=4.9.0,<5.0.0)
Requires-Dist: pyOpenSSL (>=23.0.0,<24.0.0)
Requires-Dist: python-whois (>=0.8.0,<0.9.0)
Requires-Dist: requests (>=2.28.0,<3.0.0)
Project-URL: Homepage, https://github.com/maaurors/SHINIGAMI-EYE
Project-URL: Repository, https://github.com/maaurors/SHINIGAMI-EYE
